gossipcat/__init__.py
gossipcat/__version__.py
gossipcat/deep/Autoencoder.py
gossipcat/deep/GraphCN.py
gossipcat/deep/StyleTransfer.py
gossipcat/deep/__init__.py
gossipcat/dev/CAT.py
gossipcat/dev/Configure.py
gossipcat/dev/Deep.py
gossipcat/dev/FileSys.py
gossipcat/dev/Logging.py
gossipcat/dev/Preprocess.py
gossipcat/dev/XGB.py
gossipcat/dev/__init__.py
gossipcat/graph/Draw.py
gossipcat/graph/GraphFE.py
gossipcat/graph/__init__.py
gossipcat/lab/Baseline.py
gossipcat/lab/Cluster.py
gossipcat/lab/Comparison.py
gossipcat/lab/CrossValidation.py
gossipcat/lab/Explain.py
gossipcat/lab/Feature.py
gossipcat/lab/FeatureEng.py
gossipcat/lab/Glimpse.py
gossipcat/lab/GridSearch.py
gossipcat/lab/Hyper.py
gossipcat/lab/Linkage.py
gossipcat/lab/Potential.py
gossipcat/lab/Presentation.py
gossipcat/lab/Report.py
gossipcat/lab/SimAnneal.py
gossipcat/lab/Similarity.py
gossipcat/lab/Stack.py
gossipcat/lab/TimeSeries.py
gossipcat/lab/Tune.py
gossipcat/lab/__init__.py
gossipcat/lab/util.py
gossipcat/play/__init__.py
gossipcat/play/plot.py
gossipcat/time/NPG.py
gossipcat/time/TS.py
gossipcat/time/__init__.py
gossipcat-0.3.36.dist-info/LICENSE
gossipcat-0.3.36.dist-info/METADATA
gossipcat-0.3.36.dist-info/WHEEL
gossipcat-0.3.36.dist-info/top_level.txt
gossipcat-0.3.36.dist-info/RECORD
