Metadata-Version: 2.1
Name: gossipcat
Version: 0.3.36
Summary: GossipCat, A Cat Who Is Always Gossiping.
Home-page: https://github.com/Ewen2015/GossipCat
Author: Ewen Wang
Author-email: wolfgangwong2012@gmail.com
License: Apache License 2.0
Platform: UNKNOWN
Classifier: License :: OSI Approved :: Apache Software License
Classifier: Programming Language :: Python :: 3.8
Requires-Dist: pandas
Requires-Dist: numpy
Requires-Dist: matplotlib
Requires-Dist: xgboost
Requires-Dist: catboost
Requires-Dist: scikit-learn
